quick_doc_ui/__init__.py
quick_doc_ui/backend.py
quick_doc_ui/GUI/index.html
quick_doc_ui/GUI/script.js
quick_doc_ui/GUI/style.css
quick_doc_ui/visual.py
quick_doc_ui-1.1.1.dist-info/entry_points.txt
quick_doc_ui-1.1.1.dist-info/METADATA
quick_doc_ui-1.1.1.dist-info/WHEEL
quick_doc_ui-1.1.1.dist-info/RECORD
