Metadata-Version: 2.1
Name: quick-doc-ui
Version: 1.1.1
Summary: UI docomentation generator
License: MIT
Author: Dmytro
Author-email: sinica911@gmail.com
Requires-Python: >=3.10,<4.0
Classifier: License :: OSI Approved :: MIT License
Classifier: Programming Language :: Python :: 3
Classifier: Programming Language :: Python :: 3.10
Classifier: Programming Language :: Python :: 3.11
Classifier: Programming Language :: Python :: 3.12
Classifier: Programming Language :: Python :: 3.13
Requires-Dist: eel (>=0.18.1,<0.19.0)
Requires-Dist: quick-doc-py (>=1.0.0,<2.0.0)
